cmfapi/__init__.py
cmfapi/client.py
cmfapi/conn.py
cmfapi-0.0.2.dist-info/licenses/LICENSE
cmfapi-0.0.2.dist-info/METADATA
cmfapi-0.0.2.dist-info/WHEEL
cmfapi-0.0.2.dist-info/top_level.txt
cmfapi-0.0.2.dist-info/RECORD
