Metadata-Version: 2.4
Name: cmfapi
Version: 0.0.2
Summary: Python API Client for CMF
Home-page: https://github.com/atripathy86/cmfapi
Author: Aalap Tripathy
Author-email: Aalap Tripathy <atripathy.bulk@gmail.com>
License: Apache
Project-URL: Homepage, https://github.com/atripathy86/cmfapi
Project-URL: Documentation, https://github.com/atripathy86/cmfapi
Project-URL: Source, https://github.com/atripathy86/cmfapi
Project-URL: Issues, https://github.com/atripathy86/cmfapi/issues
Keywords: cmf,metadata,common metadata framework,api,client
Classifier: Development Status :: 4 - Beta
Classifier: Intended Audience :: Developers
Classifier: License :: OSI Approved :: MIT License
Classifier: Programming Language :: Python :: 3
Classifier: Programming Language :: Python :: 3.8
Classifier: Programming Language :: Python :: 3.9
Classifier: Programming Language :: Python :: 3.10
Classifier: Programming Language :: Python :: 3.11
Classifier: Programming Language :: Python :: 3.12
Requires-Python: >=3.6
License-File: LICENSE
Requires-Dist: requests>=2.26.0
Dynamic: author
Dynamic: home-page
Dynamic: license-file
Dynamic: requires-python
